Workbook

Sheet Récap
D4: Point anticipations au 04/03/2026
D5: GESTION DES REMBOURSEMENTS (Tombée Échéance du 05/03/2026)
B6: CODE | C6: AGENCE | D6: PREV | E6: REAL | F6: % NBRE | G6: GAP Nbre | H6: PREV | I6: REAL | J6: % VOL | K6: GAP Vol
B7: M100 | C7: BONOUA | D7: ='Listing tombées'!A122 -> 119 | E7: ='Listing tombées'!V122 -> 87 | F7: =E7/D7 -> 0.73109244 | G7: =E7-D7 -> -32 | H7: ='Listing tombées'!J122 -> 13247996 | I7: ='Listing tombées'!S122 -> 10690662 | J7: =I7/H7 -> 0.80696446 | K7: =I7-H7 -> -2557334
B8: M200 | C8: ABOISSO | D8: ='Listing tombées'!A154 -> 31 | E8: ='Listing tombées'!V154 -> 24 | F8: =E8/D8 -> 0.77419355 | G8: =E8-D8 -> -7 | H8: ='Listing tombées'!J154 -> 3415814 | I8: ='Listing tombées'!S154 -> 2956359 | J8: =I8/H8 -> 0.8654918 | K8: =I8-H8 -> -459455
B9: M300 | C9: GRAND-BASSAM | D9: ='Listing tombées'!A308 -> 153 | E9: ='Listing tombées'!V308 -> 81 | F9: =E9/D9 -> 0.52941176 | G9: =E9-D9 -> -72 | H9: ='Listing tombées'!J308 -> 26359627 | I9: ='Listing tombées'!S308 -> 14185773 | J9: =I9/H9 -> 0.53816289 | K9: =I9-H9 -> -12173854
B10: M400 | C10: AGBOVILLE | D10: ='Listing tombées'!A419 -> 110 | E10: ='Listing tombées'!V419 -> 83 | F10: =E10/D10 -> 0.75454545 | G10: =E10-D10 -> -27 | H10: ='Listing tombées'!J419 -> 13053262 | I10: ='Listing tombées'!S419 -> 11081003 | J10: =I10/H10 -> 0.84890681 | K10: =I10-H10 -> -1972259
B11: M500 | C11: TIASSALE | D11: ='Listing tombées'!A559 -> 139 | E11: ='Listing tombées'!V559 -> 97 | F11: =E11/D11 -> 0.69784173 | G11: =E11-D11 -> -42 | H11: ='Listing tombées'!J559 -> 10501270 | I11: ='Listing tombées'!S559 -> 8097605 | J11: =I11/H11 -> 0.77110721 | K11: =I11-H11 -> -2403665
B12: M510 | C12: DIVO | D12: ='Listing tombées'!A599 -> 39 | E12: ='Listing tombées'!V599 -> 25 | F12: =E12/D12 -> 0.64102564 | G12: =E12-D12 -> -14 | H12: ='Listing tombées'!J599 -> 4417040 | I12: ='Listing tombées'!S599 -> 3839586 | J12: =I12/H12 -> 0.86926675 | K12: =I12-H12 -> -577454
B13: M600 | C13: ADZOPE | D13: ='Listing tombées'!A674 -> 74 | E13: ='Listing tombées'!V674 -> 64 | F13: =E13/D13 -> 0.86486486 | G13: =E13-D13 -> -10 | H13: ='Listing tombées'!J674 -> 8838342 | I13: ='Listing tombées'!S674 -> 7890066 | J13: =I13/H13 -> 0.89270884 | K13: =I13-H13 -> -948276
B14: M700 | C14: GRAND-LAHOU | D14: ='Listing tombées'!A724 -> 49 | E14: ='Listing tombées'!V724 -> 38 | F14: =E14/D14 -> 0.7755102 | G14: =E14-D14 -> -11 | H14: ='Listing tombées'!J724 -> 5111652 | I14: ='Listing tombées'!S724 -> 4431544 | J14: =I14/H14 -> 0.86694947 | K14: =I14-H14 -> -680108
B15: M710 | C15: DABOU | D15: ='Listing tombées'!A801 -> 76 | E15: ='Listing tombées'!V801 -> 48 | F15: =E15/D15 -> 0.63157895 | G15: =E15-D15 -> -28 | H15: ='Listing tombées'!J801 -> 12911371 | I15: ='Listing tombées'!S801 -> 10308463 | J15: =I15/H15 -> 0.79840189 | K15: =I15-H15 -> -2602908
B16: TOTAL | D16: =SUM(D7:D15) -> 790 | E16: =SUM(E7:E15) -> 547 | F16: =E16/D16 -> 0.69240506 | G16: =SUM(G7:G15) -> -243 | H16: =SUM(H7:H15) -> 97856374 | I16: =SUM(I7:I15) -> 73481061 | J16: =I16/H16 -> 0.75090725 | K16: =SUM(K7:K15) -> -24375313
C25: AGENCE | D25: % NBRE
C26: BONOUA | D26: 0.73109244
C27: ABOISSO | D27: 0.77419355
C28: GRAND-BASSAM | D28: 0.52941176
C29: AGBOVILLE | D29: 0.75454545
C30: TIASSALE | D30: 0.69784173
C31: DIVO | D31: 0.64102564
C32: ADZOPE | D32: 0.86486486
C33: GRAND-LAHOU | D33: 0.7755102
C34: DABOU | D34: 0.63157895

Sheet Listing tombées
Y1: COMMENTAIRES
A2: N° | B2: Agence | C2: Agent de crédit | D2: Dossier | E2: Code | F2: N° manuel | G2: Client | H2: Produit | I2: Date échéance | J2: Total échéance | K2: Intérêt | L2: Capital | M2: Epargne | N2: Frais de gestion | O2: Commission | P2: Contrat | Q2: Solde | S2: Montant versé | T2: Reste à payer | U2: Statut | V2: Réal Nbre | W2: % Nbre | X2: % Vol | Y2: Montant récupéré | Z2: OBSERVATIONS
A3: 1 | B3: BONOUA | D3: M100PRT2025047U00100 | E3: M10000417 | F3: A00200000417 | G3: N`DAH MANOU 0707938591 | H3: Crédit BFR | I3: 46086 | J3: =SUM(K3:O3) -> 173672 | K3: 34521 | L3: 124993 | M3: 13158 | N3: 0 | O3: 1000 | P3: 11071 | Q3: 315016 | R3: =Q3/J3 -> 1.813856 | S3: =J3 -> 173672 | T3: =S3-J3 -> 0 | U3: OK | V3: 1 | W3: =V3/A3 -> 1 | X3: =S3/J3 -> 1
A4: 1 | B4: BONOUA | D4: M100PRT2025051U00083 | E4: M10000963 | F4: A00200000963 | G4: AMAN SOMALE MARGUERITE 0707178363 | H4: Crédit BFR | I4: 46086 | J4: =SUM(K4:O4) -> 101013 | K4: 8517 | L4: 83163 | M4: 8333 | N4: 0 | O4: 1000 | P4: 10903 | Q4: 215970 | R4: =Q4/J4 -> 2.1380416 | S4: =J4 -> 101013 | T4: =S4-J4 -> 0 | U4: OK | V4: 1 | W4: =V4/A4 -> 1 | X4: =S4/J4 -> 1
A5: 1 | B5: BONOUA | D5: M100PRT2025048U00048 | E5: M10001040 | F5: A00200001040 | G5: ASSOHOUN AYA 0707837244 | H5: Crédit BFR | I5: 46086 | J5: =SUM(K5:O5) -> 70362 | K5: 13281 | L5: 50525 | M5: 5556 | N5: 0 | O5: 1000 | P5: 11058 | Q5: 232294 | R5: =Q5/J5 -> 3.3014127 | S5: =J5 -> 70362 | T5: =S5-J5 -> 0 | U5: OK | V5: 1 | W5: =V5/A5 -> 1 | X5: =S5/J5 -> 1
A6: 1 | B6: BONOUA | D6: M100PRT2025047U00119 | E6: M10001071 | F6: A00200001071 | G6: KONE EPOUSE KONATE ASSETOU 0709189429 | H6: Crédit BFR | I6: 46086 | J6: =SUM(K6:O6) -> 70362 | K6: 20219 | L6: 43587 | M6: 5556 | N6: 0 | O6: 1000 | P6: 11139 | Q6: 94767 | R6: =Q6/J6 -> 1.3468492 | S6: =J6 -> 70362 | T6: =S6-J6 -> 0 | U6: OK | V6: 1 | W6: =V6/A6 -> 1 | X6: =S6/J6 -> 1
A7: 1 | B7: BONOUA | D7: M100PRT2026047U00001 | E7: M10001584 | F7: A00200001584 | G7: ETTIA ANAN LYDIE 0140787680 | H7: Crédit BFR | I7: 46086 | J7: =SUM(K7:O7) -> 139723 | K7: 40438 | L7: 87174 | M7: 11111 | N7: 0 | O7: 1000 | P7: 11138 | Q7: 271205 | R7: =Q7/J7 -> 1.941019 | S7: =J7 -> 139723 | T7: =S7-J7 -> 0 | U7: OK | V7: 1 | W7: =V7/A7 -> 1 | X7: =S7/J7 -> 1
A8: 1 | B8: BONOUA | D8: M100PRT2025047U00101 | E8: M10001610 | F8: A00200001610 | G8: NOGBOU EPOUSE ANIBE AKISSI ELIANE - PELAGIE 0707403728 | H8: Crédit BFR | I8: 46086 | J8: =SUM(K8:O8) -> 105042 | K8: 19963 | L8: 75746 | M8: 8333 | N8: 0 | O8: 1000 | P8: 11081 | Q8: 235403 | R8: =Q8/J8 -> 2.2410369 | S8: =J8 -> 105042 | T8: =S8-J8 -> 0 | U8: OK | V8: 1 | W8: =V8/A8 -> 1 | X8: =S8/J8 -> 1
A9: 1 | B9: BONOUA | D9: M100PRT2025048U00047 | E9: M10001725 | F9: A00200001725 | G9: YAO AFFLA MARIE MADELEINE 0708976741 | H9: Crédit investissement | I9: 46086 | J9: =SUM(K9:O9) -> 100372 | K9: 13808 | L9: 77872 | M9: 7692 | N9: 0 | O9: 1000 | P9: 11082 | Q9: 38765 | R9: =Q9/J9 -> 0.38621329 | S9: =Q9 -> 38765 | T9: =S9-J9 -> -61607 | U9: NOK | W9: =V9/A9 -> 0 | X9: =S9/J9 -> 0.38621329
A10: 1 | B10: BONOUA | D10: M100PRT2025047U00103 | E10: M10001759 | F10: A00200001759 | G10: ELLOH ADJIMAN MADELEINE 0153637707 | H10: Crédit BFR | I10: 46086 | J10: =SUM(K10:O10) -> 150058 | K10: 20712 | L10: 116808 | M10: 11538 | N10: 0 | O10: 1000 | P10: 11096 | Q10: 73022 | R10: =Q10/J10 -> 0.48662517 | S10: =Q10 -> 73022 | T10: =S10-J10 -> -77036 | U10: NOK | W10: =V10/A10 -> 0 | X10: =S10/J10 -> 0.48662517
A11: 1 | B11: BONOUA | D11: M100PRT2025051U00141 | E11: M10002064 | F11: A00200002064 | G11: ADJOBI epouse ADIKOTEKE ABA DANIELLE ESTHER 0757270358 | H11: Crédit BFR | I11: 46086 | J11: =SUM(K11:O11) -> 201027 | K11: 21471 | L11: 161889 | M11: 16667 | N11: 0 | O11: 1000 | P11: 10986 | Q11: 314351 | R11: =Q11/J11 -> 1.5637253 | S11: =J11 -> 201027 | T11: =S11-J11 -> 0 | U11: OK | V11: 1 | W11: =V11/A11 -> 1 | X11: =S11/J11 -> 1
A12: 1 | B12: BONOUA | D12: M100PRT2025049U00088 | E12: M10002216 | F12: A00200002216 | G12: TOUNI TIANA CHANTAL 0747341870 | H12: Crédit BFR | I12: 46086 | J12: =SUM(K12:O12) -> 82611 | K12: 12217 | L12: 62727 | M12: 6667 | N12: 0 | O12: 1000 | P12: 11029 | Q12: 237369 | R12: =Q12/J12 -> 2.8733341 | S12: =J12 -> 82611 | T12: =S12-J12 -> 0 | U12: OK | V12: 1 | W12: =V12/A12 -> 1 | X12: =S12/J12 -> 1
A13: 1 | B13: BONOUA | D13: M100PRT2025048U00001 | E13: M10002408 | F13: A00200002408 | G13: ABA ASSOHOUN MODESTINE LARISSA 0703348303 | H13: Crédit investissement | I13: 46086 | J13: =SUM(K13:O13) -> 278445 | K13: 26449 | L13: 228774 | M13: 22222 | N13: 0 | O13: 1000 | P13: 10681 | Q13: 51232 | R13: =Q13/J13 -> 0.18399325 | S13: =Q13 -> 51232 | T13: =S13-J13 -> -227213 | U13: NOK | W13: =V13/A13 -> 0 | X13: =S13/J13 -> 0.18399325
A14: 1 | B14: BONOUA | D14: M100PRT2025049U00109 | E14: M10002455 | F14: A00200002455 | G14: AYEMOU EPOUSE MOULO BISSIE MODESTINE 0546123869 | H14: Crédit BFR | I14: 46086 | J14: =SUM(K14:O14) -> 101013 | K14: 12883 | L14: 78797 | M14: 8333 | N14: 0 | O14: 1000 | P14: 11108 | Q14: 131133 | R14: =Q14/J14 -> 1.2981794 | S14: =J14 -> 101013 | T14: =S14-J14 -> 0 | U14: OK | V14: 1 | W14: =V14/A14 -> 1 | X14: =S14/J14 -> 1
A15: 1 | B15: BONOUA | D15: M100PRT2025047U00078 | E15: M10002575 | F15: A00200002575 | G15: KOUASSI ESTELLE 0152512140 | H15: Crédit BFR | I15: 46086 | J15: =SUM(K15:O15) -> 101013 | K15: 7353 | L15: 84327 | M15: 8333 | N15: 0 | O15: 1000 | P15: 10872 | Q15: 194173 | R15: =Q15/J15 -> 1.9222575 | S15: =J15 -> 101013 | T15: =S15-J15 -> 0 | U15: OK | V15: 1 | W15: =V15/A15 -> 1 | X15: =S15/J15 -> 1
A16: 1 | B16: BONOUA | D16: M100PRT2026049U00002 | E16: M10002672 | F16: A00200002672 | G16: KOUADIO EPOUSE ELETE AKOUA FIENIN ROSE 0709673206 | H16: Crédit investissement | I16: 46086 | J16: =SUM(K16:O16) -> 51007 | K16: 10356 | L16: 35484 | M16: 4167 | N16: 0 | O16: 1000 | P16: 11135 | Q16: 201378 | R16: =Q16/J16 -> 3.9480463 | S16: =J16 -> 51007 | T16: =S16-J16 -> 0 | U16: OK | V16: 1 | W16: =V16/A16 -> 1 | X16: =S16/J16 -> 1
A17: 1 | B17: BONOUA | D17: M100PRT2025049U00107 | E17: M10002722 | F17: A00200002722 | G17: KRAIDY M`MIN BERTINE 0140784518 | H17: Crédit BFR | I17: 46086 | J17: =SUM(K17:O17) -> 51007 | K17: 6441 | L17: 39399 | M17: 4167 | N17: 0 | O17: 1000 | P17: 11097 | Q17: 231803 | R17: =Q17/J17 -> 4.5445331 | S17: =J17 -> 51007 | T17: =S17-J17 -> 0 | U17: OK | V17: 1 | W17: =V17/A17 -> 1 | X17: =S17/J17 -> 1
A18: 1 | B18: BONOUA | D18: M100PRT2025048U00016 | E18: M10002728 | F18: A00200002728 | G18: KACOU AGATHE 0101311916 | H18: Crédit BFR | I18: 46086 | J18: =SUM(K18:O18) -> 201027 | K18: 14618 | L18: 168742 | M18: 16667 | N18: 0 | O18: 1000 | P18: 10861 | Q18: 118728 | R18: =Q18/J18 -> 0.59060723 | S18: =Q18 -> 118728 | T18: =S18-J18 -> -82299 | U18: NOK | W18: =V18/A18 -> 0 | X18: =S18/J18 -> 0.59060723
A19: 1 | B19: BONOUA | D19: M100PRT2025048U00018 | E19: M10002962 | F19: A00200002962 | G19: NIAMKE ALLOUA DELPHINE 0103188157 | H19: Crédit investissement | I19: 46086 | J19: =SUM(K19:O19) -> 123417 | K19: 13123 | L19: 99294 | M19: 10000 | N19: 0 | O19: 1000 | P19: 10873 | Q19: 116182 | R19: =Q19/J19 -> 0.94137761 | S19: =Q19 -> 116182 | T19: =S19-J19 -> -7235 | U19: NOK | W19: =V19/A19 -> 0 | X19: =S19/J19 -> 0.94137761
A20: 1 | B20: BONOUA | D20: M100PRT2025051U00121 | E20: M10002985 | F20: A00200002985 | G20: AKOI VALOU REGINA MARIE SILVIANNE 0101553217 | H20: Crédit BFR | I20: 46086 | J20: =SUM(K20:O20) -> 105042 | K20: 16857 | L20: 78852 | M20: 8333 | N20: 0 | O20: 1000 | P20: 10958 | Q20: 274160 | R20: =Q20/J20 -> 2.6100036 | S20: =J20 -> 105042 | T20: =S20-J20 -> 0 | U20: OK | V20: 1 | W20: =V20/A20 -> 1 | X20: =S20/J20 -> 1
A21: 1 | B21: BONOUA | D21: M100PRT2025046U00029 | E21: M10003325 | F21: A00200003325 | G21: CISSE AICHA 0757399758 | H21: Crédit BFR | I21: 46086 | J21: =SUM(K21:O21) -> 131017 | K21: 11081 | L21: 108103 | M21: 10833 | N21: 0 | O21: 1000 | P21: 10904 | Q21: 261902 | R21: =Q21/J21 -> 1.9989925 | S21: =J21 -> 131017 | T21: =S21-J21 -> 0 | U21: OK | V21: 1 | W21: =V21/A21 -> 1 | X21: =S21/J21 -> 1
A22: 1 | B22: BONOUA | D22: M100PRT2025048U00053 | E22: M10003345 | F22: A00200003345 | G22: AHOURE ADJOBA HORTENSE 0707080673 | H22: Crédit BFR | I22: 46086 | J22: =SUM(K22:O22) -> 100372 | K22: 13808 | L22: 77872 | M22: 7692 | N22: 0 | O22: 1000 | P22: 11109 | Q22: 135352 | R22: =Q22/J22 -> 1.3485036 | S22: =J22 -> 100372 | T22: =S22-J22 -> 0 | U22: OK | V22: 1 | W22: =V22/A22 -> 1 | X22: =S22/J22 -> 1
A23: 1 | B23: BONOUA | D23: M100PRT2025047U00077 | E23: M10003520 | F23: A00200003520 | G23: ZANMENOU ALIMATOU SADIA 07-57-12-13-20/01-52-41-60-47 | H23: Crédit BFR | I23: 46086 | J23: =SUM(K23:O23) -> 71009 | K23: 5147 | L23: 59029 | M23: 5833 | N23: 0 | O23: 1000 | P23: 10874 | Q23: 12556 | R23: =Q23/J23 -> 0.17682266 | S23: =Q23 -> 12556 | T23: =S23-J23 -> -58453 | U23: NOK | W23: =V23/A23 -> 0 | X23: =S23/J23 -> 0.17682266
A24: 1 | B24: BONOUA | D24: M100PRT2025049U00091 | E24: M10003660 | F24: A00200003660 | G24: FATOUMATA CAMARA 0748131421 | H24: Crédit BFR | I24: 46086 | J24: =SUM(K24:O24) -> 151020 | K24: 17607 | L24: 119913 | M24: 12500 | N24: 0 | O24: 1000 | P24: 11050 | Q24: 448053 | R24: =Q24/J24 -> 2.9668455 | S24: =J24 -> 151020 | T24: =S24-J24 -> 0 | U24: OK | V24: 1 | W24: =V24/A24 -> 1 | X24: =S24/J24 -> 1
A25: 1 | B25: BONOUA | D25: M100PRT2025048U00051 | E25: M10003905 | F25: A00200003905 | G25: KOUAMELAN M`PIKE SABINE 0502477955 | H25: Crédit BFR | I25: 46086 | J25: =SUM(K25:O25) -> 42728 | K25: 8745 | L25: 29825 | M25: 3158 | N25: 0 | O25: 1000 | P25: 11122 | Q25: 79230 | R25: =Q25/J25 -> 1.8542876 | S25: =J25 -> 42728 | T25: =S25-J25 -> 0 | U25: OK | V25: 1 | W25: =V25/A25 -> 1 | X25: =S25/J25 -> 1
A26: 1 | B26: BONOUA | D26: M100PRT2025049U00079 | E26: M10004052 | F26: A00200004052 | G26: MITOKPE SEDOMON NADEGE PULCHERIE 0143114710 | H26: Crédit BFR | I26: 46086 | J26: =SUM(K26:O26) -> 201027 | K26: 21359 | L26: 162001 | M26: 16667 | N26: 0 | O26: 1000 | P26: 10991 | Q26: 342613 | R26: =Q26/J26 -> 1.7043134 | S26: =J26 -> 201027 | T26: =S26-J26 -> 0 | U26: OK | V26: 1 | W26: =V26/A26 -> 1 | X26: =S26/J26 -> 1
A27: 1 | B27: BONOUA | D27: M100PRT2025048U00044 | E27: M10004151 | F27: A00200004151 | G27: FOFANA AICHA 0140221266 | H27: Crédit BFR | I27: 46086 | J27: =SUM(K27:O27) -> 71009 | K27: 9047 | L27: 55129 | M27: 5833 | N27: 0 | O27: 1000 | P27: 11084 | Q27: 37574 | R27: =Q27/J27 -> 0.52914419 | S27: =Q27 -> 37574 | T27: =S27-J27 -> -33435 | U27: NOK | W27: =V27/A27 -> 0 | X27: =S27/J27 -> 0.52914419
A28: 1 | B28: BONOUA | D28: M100PRT2025049U00111 | E28: M10004301 | F28: A00200004301 | G28: KANTE FANTA 0506516512 | H28: Crédit BFR | I28: 46086 | J28: =SUM(K28:O28) -> 31004 | K28: 6214 | L28: 21290 | M28: 2500 | N28: 0 | O28: 1000 | P28: 11134 | Q28: 37724 | R28: =Q28/J28 -> 1.2167462 | S28: =J28 -> 31004 | T28: =S28-J28 -> 0 | U28: OK | V28: 1 | W28: =V28/A28 -> 1 | X28: =S28/J28 -> 1
A29: 1 | B29: BONOUA | D29: M100PRT2025049U00112 | E29: M10004306 | F29: A00200004306 | G29: DIARRA SETOU 0555308997 | H29: Crédit BFR | I29: 46086 | J29: =SUM(K29:O29) -> 31004 | K29: 6214 | L29: 21290 | M29: 2500 | N29: 0 | O29: 1000 | P29: 11136 | Q29: 46571 | R29: =Q29/J29 -> 1.5020965 | S29: =J29 -> 31004 | T29: =S29-J29 -> 0 | U29: OK | V29: 1 | W29: =V29/A29 -> 1 | X29: =S29/J29 -> 1
A30: 1 | B30: BONOUA | D30: M100PRT2025046U00042 | E30: M10004414 | F30: A00200004414 | G30: OBROU LARISSA ESTELLE 0749935475 | H30: Crédit BFR | I30: 46086 | J30: =SUM(K30:O30) -> 151020 | K30: 17638 | L30: 119882 | M30: 12500 | N30: 0 | O30: 1000 | P30: 11033 | Q30: 242215 | R30: =Q30/J30 -> 1.6038604 | S30: =J30 -> 151020 | T30: =S30-J30 -> 0 | U30: OK | V30: 1 | W30: =V30/A30 -> 1 | X30: =S30/J30 -> 1
A31: 1 | B31: BONOUA | D31: M100PRT2025048U00042 | E31: M10004618 | F31: A00200004618 | G31: KANGAH ATTOUOH LAURA YVANA 07-67-11-73-79/01-43-18-40-19 | H31: Crédit BFR | I31: 46086 | J31: =SUM(K31:O31) -> 105042 | K31: 19973 | L31: 75736 | M31: 8333 | N31: 0 | O31: 1000 | P31: 11066 | Q31: 202037 | R31: =Q31/J31 -> 1.9233925 | S31: =J31 -> 105042 | T31: =S31-J31 -> 0 | U31: OK | V31: 1 | W31: =V31/A31 -> 1 | X31: =S31/J31 -> 1
A32: 1 | B32: BONOUA | D32: M100PRT2025049U00113 | E32: M10004769 | F32: A00200004769 | G32: DIARRA AMINATA 0748277299 | H32: Crédit BFR | I32: 46086 | J32: =SUM(K32:O32) -> 71009 | K32: 14499 | L32: 49677 | M32: 5833 | N32: 0 | O32: 1000 | P32: 11137 | Q32: 21876 | R32: =Q32/J32 -> 0.30807362 | S32: =Q32 -> 21876 | T32: =S32-J32 -> -49133 | U32: NOK | W32: =V32/A32 -> 0 | X32: =S32/J32 -> 0.30807362
A33: 1 | B33: BONOUA | D33: M100PRT2025048U00012 | E33: M10004813 | F33: A00200004813 | G33: KADJO MANGUE ELISABETH 0777797121 | H33: Crédit BFR | I33: 46086 | J33: =SUM(K33:O33) -> 251033 | K33: 15241 | L33: 213959 | M33: 20833 | N33: 0 | O33: 1000 | P33: 10849 | Q33: 22784 | R33: =Q33/J33 -> 0.090760976 | S33: =Q33 -> 22784 | T33: =S33-J33 -> -228249 | U33: NOK | W33: =V33/A33 -> 0 | X33: =S33/J33 -> 0.090760976
A34: 1 | B34: BONOUA | D34: M100PRT2025047U00087 | E34: M10004826 | F34: A00200004826 | G34: SORO FOUNZOGORY 0173718140 | H34: Crédit BFR | I34: 46086 | J34: =SUM(K34:O34) -> 71009 | K34: 5091 | L34: 59085 | M34: 5833 | N34: 0 | O34: 1000 | P34: 10890 | Q34: 128497 | R34: =Q34/J34 -> 1.8095875 | S34: =J34 -> 71009 | T34: =S34-J34 -> 0 | U34: OK | V34: 1 | W34: =V34/A34 -> 1 | X34: =S34/J34 -> 1
A35: 1 | B35: BONOUA | D35: M100PRT2025051U00085 | E35: M10004895 | F35: A00200004895 | G35: BOSSON épouse KOUAME AHISSIA MARIE 0707584780 | H35: Crédit BFR | I35: 46086 | J35: =SUM(K35:O35) -> 51007 | K35: 4258 | L35: 41582 | M35: 4167 | N35: 0 | O35: 1000 | P35: 10906 | Q35: 291851 | R35: =Q35/J35 -> 5.7217833 | S35: =J35 -> 51007 | T35: =S35-J35 -> 0 | U35: OK | V35: 1 | W35: =V35/A35 -> 1 | X35: =S35/J35 -> 1
A36: 1 | B36: BONOUA | D36: M100PRT2025049U00106 | E36: M10005035 | F36: A00200005035 | G36: KONE BEZOU MARIE ROLANDE 0747639001 | H36: Crédit BFR | I36: 46086 | J36: =SUM(K36:O36) -> 51007 | K36: 6441 | L36: 39399 | M36: 4167 | N36: 0 | O36: 1000 | P36: 11110 | Q36: 24124 | R36: =Q36/J36 -> 0.47295469 | S36: =Q36 -> 24124 | T36: =S36-J36 -> -26883 | U36: NOK | W36: =V36/A36 -> 0 | X36: =S36/J36 -> 0.47295469
A37: 1 | B37: BONOUA | D37: M100PRT2025051U00148 | E37: M10005054 | F37: A00200005054 | G37: ELLOH épouse NOGBOU AMON GENEVIEVE 0103515147 | H37: Crédit investissement | I37: 46086 | J37: =SUM(K37:O37) -> 51007 | K37: 5876 | L37: 39964 | M37: 4167 | N37: 0 | O37: 1000 | P37: 11034 | Q37: 118530 | R37: =Q37/J37 -> 2.3237987 | S37: =J37 -> 51007 | T37: =S37-J37 -> 0 | U37: OK | V37: 1 | W37: =V37/A37 -> 1 | X37: =S37/J37 -> 1
A38: 1 | B38: BONOUA | D38: M100PRT2025048U00015 | E38: M10005069 | F38: A00200005069 | G38: ATTOUMOU AFFLA MARIE DIANA 0747595321 | H38: Crédit BFR | I38: 46086 | J38: =SUM(K38:O38) -> 501067 | K38: 36618 | L38: 421782 | M38: 41667 | N38: 0 | O38: 1000 | P38: 10875 | Q38: 0 | R38: =Q38/J38 -> 0 | S38: =Q38 -> 0 | T38: =S38-J38 -> -501067 | U38: NOK | W38: =V38/A38 -> 0 | X38: =S38/J38 -> 0
A39: 1 | B39: BONOUA | D39: M100PRT2025046U00061 | E39: M10005147 | F39: A00200005147 | G39: ADJA ADJOBA ISABELLE 0505794026 | H39: Crédit BFR | I39: 46086 | J39: =SUM(K39:O39) -> 20874 | K39: 2762 | L39: 15574 | M39: 1538 | N39: 0 | O39: 1000 | P39: 11100 | Q39: 68891 | R39: =Q39/J39 -> 3.3003258 | S39: =J39 -> 20874 | T39: =S39-J39 -> 0 | U39: OK | V39: 1 | W39: =V39/A39 -> 1 | X39: =S39/J39 -> 1
A40: 1 | B40: BONOUA | D40: M100PRT2025046U00063 | E40: M10005199 | F40: A00200005199 | G40: ADJOBI ADJOBA FLORENCE ESTELLE 0757419822 | H40: Crédit BFR | I40: 46086 | J40: =SUM(K40:O40) -> 199745 | K40: 27616 | L40: 155744 | M40: 15385 | N40: 0 | O40: 1000 | P40: 11101 | Q40: 471393 | R40: =Q40/J40 -> 2.359974 | S40: =J40 -> 199745 | T40: =S40-J40 -> 0 | U40: OK | V40: 1 | W40: =V40/A40 -> 1 | X40: =S40/J40 -> 1
A41: 1 | B41: BONOUA | D41: M100PRT2025046U00024 | E41: M10005253 | F41: A00200005253 | G41: ESSI ANGUETTE JACQUELINE MARIE MADELEINE 0142834210 | H41: Crédit BFR | I41: 46086 | J41: =SUM(K41:O41) -> 221029 | K41: 13412 | L41: 188284 | M41: 18333 | N41: 0 | O41: 1000 | P41: 10850 | Q41: 18584 | R41: =Q41/J41 -> 0.084079465 | S41: =Q41 -> 18584 | T41: =S41-J41 -> -202445 | U41: NOK | W41: =V41/A41 -> 0 | X41: =S41/J41 -> 0.084079465
A42: 1 | B42: BONOUA | D42: M100PRT2025049U00078 | E42: M10005289 | F42: A00200005289 | G42: TRAORE ADJARATOU 0545961404 | H42: Crédit BFR | I42: 46086 | J42: =SUM(K42:O42) -> 51007 | K42: 5368 | L42: 40472 | M42: 4167 | N42: 0 | O42: 1000 | P42: 10999 | Q42: 110206 | R42: =Q42/J42 -> 2.1606054 | S42: =J42 -> 51007 | T42: =S42-J42 -> 0 | U42: OK | V42: 1 | W42: =V42/A42 -> 1 | X42: =S42/J42 -> 1
A43: 1 | B43: BONOUA | D43: M100PRT2025051U00081 | E43: M10005418 | F43: A00200005418 | G43: ACHIMA OCTAVIE AUBIERGE 0565697492 | H43: Crédit Santé Mucrefab | I43: 46086 | J43: =SUM(K43:O43) -> 48110 | K43: 2120 | L43: 44990 | M43: 0 | N43: 0 | O43: 1000 | P43: 10888 | Q43: 4361796 | R43: =Q43/J43 -> 90.662981 | S43: =J43 -> 48110 | T43: =S43-J43 -> 0 | U43: OK | V43: 1 | W43: =V43/A43 -> 1 | X43: =S43/J43 -> 1
A44: 1 | B44: BONOUA | D44: M100PRT2025048U00030 | E44: M10005424 | F44: A00200005424 | G44: KOUADIO épouse ATSAIN SOPIE ELISABETH 0555292109 | H44: Crédit BFR | I44: 46086 | J44: =SUM(K44:O44) -> 61008 | K44: 6462 | L44: 48546 | M44: 5000 | N44: 0 | O44: 1000 | P44: 11000 | Q44: 22957 | R44: =Q44/J44 -> 0.37629491 | S44: =Q44 -> 22957 | T44: =S44-J44 -> -38051 | U44: NOK | W44: =V44/A44 -> 0 | X44: =S44/J44 -> 0.37629491
A45: 1 | B45: BONOUA | D45: M100PRT2025047U00110 | E45: M10005430 | F45: A00200005430 | G45: TIHOUA SELEY AUDREY DORINE 0141267815 | H45: Crédit BFR | I45: 46086 | J45: =SUM(K45:O45) -> 151020 | K45: 19304 | L45: 118216 | M45: 12500 | N45: 0 | O45: 1000 | P45: 11125 | Q45: 74072 | R45: =Q45/J45 -> 0.49047808 | S45: =Q45 -> 74072 | T45: =S45-J45 -> -76948 | U45: NOK | W45: =V45/A45 -> 0 | X45: =S45/J45 -> 0.49047808
A46: 1 | B46: BONOUA | D46: M100PRT2025046U00055 | E46: M10005441 | F46: A00200005441 | G46: KARAMOKO AICHA 0757250962 | H46: Crédit BFR | I46: 46086 | J46: =SUM(K46:O46) -> 301040 | K46: 38791 | L46: 236249 | M46: 25000 | N46: 0 | O46: 1000 | P46: 11086 | Q46: 559163 | R46: =Q46/J46 -> 1.8574375 | S46: =J46 -> 301040 | T46: =S46-J46 -> 0 | U46: OK | V46: 1 | W46: =V46/A46 -> 1 | X46: =S46/J46 -> 1
A47: 1 | B47: BONOUA | D47: M100PRT2025051U00149 | E47: M10005526 | F47: A00200005526 | G47: OUAGADOUGOU GUESWENDE DIEUDONNE 0748452736 | H47: Crédit investissement | I47: 46086 | J47: =SUM(K47:O47) -> 280356 | K47: 52950 | L47: 204184 | M47: 22222 | N47: 0 | O47: 1000 | P47: 11001 | Q47: 441370 | R47: =Q47/J47 -> 1.5743198 | S47: =J47 -> 280356 | T47: =S47-J47 -> 0 | U47: OK | V47: 1 | W47: =V47/A47 -> 1 | X47: =S47/J47 -> 1
A48: 1 | B48: BONOUA | D48: M100PRT2025046U00058 | E48: M10005736 | F48: A00200005736 | G48: ASSI EPOUSE N'GUESSAN NINA TATIANA 0748147902 | H48: Crédit BFR | I48: 46086 | J48: =SUM(K48:O48) -> 70362 | K48: 13315 | L48: 50491 | M48: 5556 | N48: 0 | O48: 1000 | P48: 11036 | Q48: 129461 | R48: =Q48/J48 -> 1.8399278 | S48: =J48 -> 70362 | T48: =S48-J48 -> 0 | U48: OK | V48: 1 | W48: =V48/A48 -> 1 | X48: =S48/J48 -> 1
A49: 1 | B49: BONOUA | D49: M100PRT2025046U00056 | E49: M10005774 | F49: A00200005774 | G49: OKON N GUESSAN SOLANGE GEORGIE 01-70-59-93-20 | H49: Crédit BFR | I49: 46086 | J49: =SUM(K49:O49) -> 101013 | K49: 12930 | L49: 78750 | M49: 8333 | N49: 0 | O49: 1000 | P49: 11087 | Q49: 242143 | R49: =Q49/J49 -> 2.3971469 | S49: =J49 -> 101013 | T49: =S49-J49 -> 0 | U49: OK | V49: 1 | W49: =V49/A49 -> 1 | X49: =S49/J49 -> 1
A50: 1 | B50: BONOUA | D50: M100PRT2025051U00153 | E50: M10005799 | F50: A00200005799 | G50: KODIANE NANAN ISABELLE CHARLOTTE 05-76-12-48-27 | H50: Crédit BFR | I50: 46086 | J50: =SUM(K50:O50) -> 101013 | K50: 12924 | L50: 78756 | M50: 8333 | N50: 0 | O50: 1000 | P50: 11088 | Q50: 170170 | R50: =Q50/J50 -> 1.6846347 | S50: =J50 -> 101013 | T50: =S50-J50 -> 0 | U50: OK | V50: 1 | W50: =V50/A50 -> 1 | X50: =S50/J50 -> 1
A51: 1 | B51: BONOUA | D51: M100PRT2025051U00151 | E51: M10005803 | F51: A00200005803 | G51: NOUTAI ELISABETH 0102725092 0102725092 | H51: Crédit BFR | I51: 46086 | J51: =SUM(K51:O51) -> 105042 | K51: 19963 | L51: 75746 | M51: 8333 | N51: 0 | O51: 1000 | P51: 11089 | Q51: 166840 | R51: =Q51/J51 -> 1.5883171 | S51: =J51 -> 105042 | T51: =S51-J51 -> 0 | U51: OK | V51: 1 | W51: =V51/A51 -> 1 | X51: =S51/J51 -> 1
A52: 1 | B52: BONOUA | D52: M100PRT2025051U00151 | E52: M10005803 | F52: A00200005803 | G52: NOUTAI ELISABETH 0102725092 0102725092 | H52: Crédit BFR | I52: 46086 | J52: =SUM(K52:O52) -> 105042 | K52: 19963 | L52: 75746 | M52: 8333 | N52: 0 | O52: 1000 | P52: 11089 | Q52: 166840 | R52: =Q52/J52 -> 1.5883171 | S52: =J52 -> 105042 | T52: =S52-J52 -> 0 | U52: OK | V52: 1 | W52: =V52/A52 -> 1 | X52: =S52/J52 -> 1
A53: 1 | B53: BONOUA | D53: M100PRT2025051U00152 | E53: M10005805 | F53: A00200005805 | G53: N`TAYE M`PIKE AIMEE CHRISTIANE 0100687857 | H53: Crédit BFR | I53: 46086 | J53: =SUM(K53:O53) -> 31004 | K53: 3877 | L53: 23627 | M53: 2500 | N53: 0 | O53: 1000 | P53: 11091 | Q53: 49238 | R53: =Q53/J53 -> 1.5881177 | S53: =J53 -> 31004 | T53: =S53-J53 -> 0 | U53: OK | V53: 1 | W53: =V53/A53 -> 1 | X53: =S53/J53 -> 1
A54: 1 | B54: BONOUA | D54: M100PRT2025047U00075 | E54: M10005862 | F54: A00200005862 | G54: VOLOU GNAGO OLIVIER 0748233584 | H54: Crédit BFR | I54: 46086 | J54: =SUM(K54:O54) -> 81392 | K54: 6211 | L54: 67514 | M54: 6667 | N54: 0 | O54: 1000 | P54: 10877 | Q54: 47069 | R54: =Q54/J54 -> 0.57830008 | S54: =Q54 -> 47069 | T54: =S54-J54 -> -34323 | U54: NOK | W54: =V54/A54 -> 0 | X54: =S54/J54 -> 0.57830008
A55: 1 | B55: BONOUA | D55: M100PRT2025051U00088 | E55: M10005887 | F55: A00200005887 | G55: ASIFIWE SANDRINE 0504300019 | H55: Crédit BFR | I55: 46086 | J55: =SUM(K55:O55) -> 131017 | K55: 11072 | L55: 108112 | M55: 10833 | N55: 0 | O55: 1000 | P55: 10908 | Q55: 161424 | R55: =Q55/J55 -> 1.2320844 | S55: =J55 -> 131017 | T55: =S55-J55 -> 0 | U55: OK | V55: 1 | W55: =V55/A55 -> 1 | X55: =S55/J55 -> 1
A56: 1 | B56: BONOUA | D56: M100PRT2025046U00041 | E56: M10005910 | F56: A00200005910 | G56: MOBIO AHOU NADEGE 0789785311 | H56: Crédit BFR | I56: 46086 | J56: =SUM(K56:O56) -> 51007 | K56: 5879 | L56: 39961 | M56: 4167 | N56: 0 | O56: 1000 | P56: 11037 | Q56: 205106 | R56: =Q56/J56 -> 4.0211344 | S56: =J56 -> 51007 | T56: =S56-J56 -> 0 | U56: OK | V56: 1 | W56: =V56/A56 -> 1 | X56: =S56/J56 -> 1
A57: 1 | B57: BONOUA | D57: M100PRT2025051U00087 | E57: M10005937 | F57: A00200005937 | G57: NDA AGNIMAN JEANNE 0709611368 | H57: Crédit BFR | I57: 46086 | J57: =SUM(K57:O57) -> 81011 | K57: 6813 | L57: 66531 | M57: 6667 | N57: 0 | O57: 1000 | P57: 10909 | Q57: 112506 | R57: =Q57/J57 -> 1.3887744 | S57: =J57 -> 81011 | T57: =S57-J57 -> 0 | U57: OK | V57: 1 | W57: =V57/A57 -> 1 | X57: =S57/J57 -> 1
A58: 1 | B58: BONOUA | D58: M100PRT2025051U00154 | E58: M10005950 | F58: A00200005950 | G58: ADIOBY ADIOBY JULIEN 01-01-97-42-47/07-08-74-97-74 | H58: Crédit BFR | I58: 46086 | J58: =SUM(K58:O58) -> 81392 | K58: 10926 | L58: 62799 | M58: 6667 | N58: 0 | O58: 1000 | P58: 11090 | Q58: 189608 | R58: =Q58/J58 -> 2.3295656 | S58: =J58 -> 81392 | T58: =S58-J58 -> 0 | U58: OK | V58: 1 | W58: =V58/A58 -> 1 | X58: =S58/J58 -> 1
A59: 1 | B59: BONOUA | D59: M100PRT2025047U00026 | E59: M10005975 | F59: A00200005975 | G59: KOUADIO AMA 0757948141 | H59: Crédit BFR | I59: 46086 | J59: =SUM(K59:O59) -> 31004 | K59: 1121 | L59: 26383 | M59: 2500 | N59: 0 | O59: 1000 | P59: 10736 | Q59: 10418 | R59: =Q59/J59 -> 0.33602116 | S59: =Q59 -> 10418 | T59: =S59-J59 -> -20586 | U59: NOK | W59: =V59/A59 -> 0 | X59: =S59/J59 -> 0.33602116
A60: 1 | B60: BONOUA | D60: M100PRT2025051U00127 | E60: M10005989 | F60: A00200005989 | G60: DJEKE ROSELINE NADEGE 0103860412 | H60: Crédit BFR | I60: 46086 | J60: =SUM(K60:O60) -> 31004 | K60: 2873 | L60: 24631 | M60: 2500 | N60: 0 | O60: 1000 | P60: 10971 | Q60: 52862 | R60: =Q60/J60 -> 1.7050058 | S60: =J60 -> 31004 | T60: =S60-J60 -> 0 | U60: OK | V60: 1 | W60: =V60/A60 -> 1 | X60: =S60/J60 -> 1
A61: 1 | B61: BONOUA | D61: M100PRT2025051U00133 | E61: M10006031 | F61: A00200006031 | G61: AITE SEKA AKOHI MARC-LEGER 0152015989 | H61: Crédit Scolaire | I61: 46086 | J61: =SUM(K61:O61) -> 22401 | K61: 1421 | L61: 19980 | M61: 0 | N61: 0 | O61: 1000 | P61: 10984 | Q61: 35198 | R61: =Q61/J61 -> 1.5712691 | S61: =J61 -> 22401 | T61: =S61-J61 -> 0 | U61: OK | V61: 1 | W61: =V61/A61 -> 1 | X61: =S61/J61 -> 1
A62: 1 | B62: BONOUA | D62: M100PRT2025051U00157 | E62: M10006035 | F62: A00200006035 | G62: NOGBOU NIAMKE ALPHONSE CEDRIC 0140141343 | H62: Crédit BFR | I62: 46086 | J62: =SUM(K62:O62) -> 61008 | K62: 7734 | L62: 47274 | M62: 5000 | N62: 0 | O62: 1000 | P62: 11111 | Q62: 180274 | R62: =Q62/J62 -> 2.9549239 | S62: =J62 -> 61008 | T62: =S62-J62 -> 0 | U62: OK | V62: 1 | W62: =V62/A62 -> 1 | X62: =S62/J62 -> 1
A63: 1 | B63: BONOUA | D63: M100PRT2025051U00155 | E63: M10006038 | F63: A00200006038 | G63: OUATTARA ADAMA 0141599412 | H63: Crédit BFR | I63: 46086 | J63: =SUM(K63:O63) -> 151735 | K63: 20429 | L63: 117806 | M63: 12500 | N63: 0 | O63: 1000 | P63: 11112 | Q63: 255844 | R63: =Q63/J63 -> 1.6861238 | S63: =J63 -> 151735 | T63: =S63-J63 -> 0 | U63: OK | V63: 1 | W63: =V63/A63 -> 1 | X63: =S63/J63 -> 1
A64: 1 | B64: BONOUA | D64: M100PRT2025049U00066 | E64: M10006042 | F64: A00200006042 | G64: KONE NAHOUA 01-43-42-44-79 | H64: Crédit BFR | I64: 46086 | J64: =SUM(K64:O64) -> 51007 | K64: 4831 | L64: 41009 | M64: 4167 | N64: 0 | O64: 1000 | P64: 10960 | Q64: 579836 | R64: =Q64/J64 -> 11.367773 | S64: =J64 -> 51007 | T64: =S64-J64 -> 0 | U64: OK | V64: 1 | W64: =V64/A64 -> 1 | X64: =S64/J64 -> 1
A65: 1 | B65: BONOUA | D65: M100PRT2025051U00147 | E65: M10006067 | G65: DJEKE ANNE GERTRUDE 0779984200 | H65: Crédit BFR | I65: 46086 | J65: =SUM(K65:O65) -> 81011 | K65: 9401 | L65: 63943 | M65: 6667 | N65: 0 | O65: 1000 | P65: 11038 | Q65: 13636 | R65: =Q65/J65 -> 0.16832282 | S65: =Q65 -> 13636 | T65: =S65-J65 -> -67375 | U65: NOK | W65: =V65/A65 -> 0 | X65: =S65/J65 -> 0.16832282
A66: 1 | B66: BONOUA | D66: M100PRT2025048U00050 | E66: M10006092 | G66: KONE YACOUBA 0555545827 | H66: Crédit BFR | I66: 46086 | J66: =SUM(K66:O66) -> 100849 | K66: 14575 | L66: 77582 | M66: 7692 | N66: 0 | O66: 1000 | P66: 11113 | Q66: 21632 | R66: =Q66/J66 -> 0.2144989 | S66: =Q66 -> 21632 | T66: =S66-J66 -> -79217 | U66: NOK | W66: =V66/A66 -> 0 | X66: =S66/J66 -> 0.2144989
A67: 1 | B67: BONOUA | D67: M100PRT2025046U00043 | E67: M10006095 | G67: SIDIBE KINSA 0172978881 | H67: Crédit BFR | I67: 46086 | J67: =SUM(K67:O67) -> 301040 | K67: 35275 | L67: 239765 | M67: 25000 | N67: 0 | O67: 1000 | P67: 11039 | Q67: 837567 | R67: =Q67/J67 -> 2.7822449 | S67: =J67 -> 301040 | T67: =S67-J67 -> 0 | U67: OK | V67: 1 | W67: =V67/A67 -> 1 | X67: =S67/J67 -> 1
A68: 1 | B68: BONOUA | D68: M100PRT2025047U00084 | E68: M10006136 | G68: ASSALE épouse YAO ANGE MARINA 0585729402 | H68: Crédit BFR | I68: 46086 | J68: =SUM(K68:O68) -> 301040 | K68: 21817 | L68: 253223 | M68: 25000 | N68: 0 | O68: 1000 | P68: 10894 | Q68: 1144267 | R68: =Q68/J68 -> 3.8010464 | S68: =J68 -> 301040 | T68: =S68-J68 -> 0 | U68: OK | V68: 1 | W68: =V68/A68 -> 1 | X68: =S68/J68 -> 1
A69: 1 | B69: BONOUA | D69: M100PRT2025051U00156 | E69: M10006172 | G69: KACOU ASSIA 0747912479 | H69: Crédit BFR | I69: 46086 | J69: =SUM(K69:O69) -> 70362 | K69: 13274 | L69: 50532 | M69: 5556 | N69: 0 | O69: 1000 | P69: 11114 | Q69: 117887 | R69: =Q69/J69 -> 1.6754356 | S69: =J69 -> 70362 | T69: =S69-J69 -> 0 | U69: OK | V69: 1 | W69: =V69/A69 -> 1 | X69: =S69/J69 -> 1
A70: 1 | B70: BONOUA | D70: M100PRT2025046U00028 | E70: M10006173 | G70: OUATTARA TIEME GERMAINE EPSE ACHI 0758639684 | H70: Crédit BFR | I70: 46086 | J70: =SUM(K70:O70) -> 26003 | K70: 2131 | L70: 20789 | M70: 2083 | N70: 0 | O70: 1000 | P70: 10916 | Q70: 46150 | R70: =Q70/J70 -> 1.7747952 | S70: =J70 -> 26003 | T70: =S70-J70 -> 0 | U70: OK | V70: 1 | W70: =V70/A70 -> 1 | X70: =S70/J70 -> 1
A71: 1 | B71: BONOUA | D71: M100PRT2025048U00024 | E71: M10006206 | G71: DJOGBENOU GOUDJANOU MAWOUTIN.CH 0544505604 | H71: Crédit BFR | I71: 46086 | J71: =SUM(K71:O71) -> 51007 | K71: 3629 | L71: 42211 | M71: 4167 | N71: 0 | O71: 1000 | P71: 10895 | Q71: 77460 | R71: =Q71/J71 -> 1.5186151 | S71: =J71 -> 51007 | T71: =S71-J71 -> 0 | U71: OK | V71: 1 | W71: =V71/A71 -> 1 | X71: =S71/J71 -> 1
A72: 1 | B72: BONOUA | D72: M100PRT2026047U00003 | E72: M10006242 | G72: DOSSO MASSIATI 0797682384 | H72: Crédit BFR | I72: 46086 | J72: =SUM(K72:O72) -> 61008 | K72: 12132 | L72: 42876 | M72: 5000 | N72: 0 | O72: 1000 | P72: 11140 | Q72: 90956 | R72: =Q72/J72 -> 1.4908864 | S72: =J72 -> 61008 | T72: =S72-J72 -> 0 | U72: OK | V72: 1 | W72: =V72/A72 -> 1 | X72: =S72/J72 -> 1
A73: 1 | B73: BONOUA | D73: M100PRT2025047U00082 | E73: M10006258 | G73: N'GUESSAN KONAN FRANCK OLIVIER 0708522809 | H73: Crédit BFR | I73: 46086 | J73: =SUM(K73:O73) -> 51245 | K73: 3878 | L73: 42200 | M73: 4167 | N73: 0 | O73: 1000 | P73: 10821 | Q73: 77216 | R73: =Q73/J73 -> 1.5068007 | S73: =J73 -> 51245 | T73: =S73-J73 -> 0 | U73: OK | V73: 1 | W73: =V73/A73 -> 1 | X73: =S73/J73 -> 1
A74: 1 | B74: BONOUA | D74: M100PRT2025048U00011 | E74: M10006261 | G74: DABILA SALIMATA 0102772205 | H74: Crédit investissement | I74: 46086 | J74: =SUM(K74:O74) -> 36005 | K74: 2134 | L74: 29954 | M74: 2917 | N74: 0 | O74: 1000 | P74: 10838 | Q74: 52124 | R74: =Q74/J74 -> 1.4476878 | S74: =J74 -> 36005 | T74: =S74-J74 -> 0 | U74: OK | V74: 1 | W74: =V74/A74 -> 1 | X74: =S74/J74 -> 1
A75: 1 | B75: BONOUA | D75: M100PRT2025049U00053 | E75: M10006277 | G75: KADJOKAN BADJO ALPHONSINE 0709340614 | H75: Crédit investissement | I75: 46086 | J75: =SUM(K75:O75) -> 301040 | K75: 25420 | L75: 249620 | M75: 25000 | N75: 0 | O75: 1000 | P75: 10911 | Q75: 179856 | R75: =Q75/J75 -> 0.59744884 | S75: =Q75 -> 179856 | T75: =S75-J75 -> -121184 | U75: NOK | W75: =V75/A75 -> 0 | X75: =S75/J75 -> 0.59744884
A76: 1 | B76: BONOUA | D76: M100PRT2025048U00022 | E76: M10006288 | G76: KOUADIO KOSSONOU AIMEE LYDIE ANITA 0748085344 | H76: Crédit investissement | I76: 46086 | J76: =SUM(K76:O76) -> 101013 | K76: 7258 | L76: 84422 | M76: 8333 | N76: 0 | O76: 1000 | P76: 10866 | Q76: 127919 | R76: =Q76/J76 -> 1.2663618 | S76: =J76 -> 101013 | T76: =S76-J76 -> 0 | U76: OK | V76: 1 | W76: =V76/A76 -> 1 | X76: =S76/J76 -> 1
A77: 1 | B77: BONOUA | D77: M100PRT2025048U00027 | E77: M10006302 | G77: AHOURE AHOURE JEAN MARC APOPHIX 0554192088 | H77: Crédit BFR | I77: 46086 | J77: =SUM(K77:O77) -> 81392 | K77: 8098 | L77: 65627 | M77: 6667 | N77: 0 | O77: 1000 | P77: 10974 | Q77: 6073 | R77: =Q77/J77 -> 0.074614213 | S77: =Q77 -> 6073 | T77: =S77-J77 -> -75319 | U77: NOK | W77: =V77/A77 -> 0 | X77: =S77/J77 -> 0.074614213
A78: 1 | B78: BONOUA | D78: M100PRT2025047U00088 | E78: M10006309 | G78: SILUE SOUNGALO 0709080906 | H78: Crédit BFR | I78: 46086 | J78: =SUM(K78:O78) -> 101490 | K78: 7681 | L78: 84476 | M78: 8333 | N78: 0 | O78: 1000 | P78: 10871 | Q78: 211558 | R78: =Q78/J78 -> 2.0845206 | S78: =J78 -> 101490 | T78: =S78-J78 -> 0 | U78: OK | V78: 1 | W78: =V78/A78 -> 1 | X78: =S78/J78 -> 1
A79: 1 | B79: BONOUA | D79: M100PRT2025047U00081 | E79: M10006310 | G79: AHITE KOUASSI ERIC JEAN-MARC 0715276416 | H79: Crédit BFR | I79: 46086 | J79: =SUM(K79:O79) -> 503450 | K79: 38941 | L79: 421842 | M79: 41667 | N79: 0 | O79: 1000 | P79: 10879 | Q79: 374489 | R79: =Q79/J79 -> 0.74384547 | S79: =Q79 -> 374489 | T79: =S79-J79 -> -128961 | U79: NOK | W79: =V79/A79 -> 0 | X79: =S79/J79 -> 0.74384547
A80: 1 | B80: BONOUA | D80: M100PRT2025047U00080 | E80: M10006317 | G80: OUATTARA SOUALIHO 0152380710 | H80: Crédit investissement | I80: 46086 | J80: =SUM(K80:O80) -> 273876 | K80: 57940 | L80: 194103 | M80: 20833 | N80: 0 | O80: 1000 | P80: 10882 | Q80: 823942 | R80: =Q80/J80 -> 3.0084491 | S80: =J80 -> 273876 | T80: =S80-J80 -> 0 | U80: OK | V80: 1 | W80: =V80/A80 -> 1 | X80: =S80/J80 -> 1
A81: 1 | B81: BONOUA | D81: M100PRT2025048U00019 | E81: M10006326 | G81: YAO KOUAKOU ALEXANDRE 0152429956 | H81: Crédit BFR | I81: 46086 | J81: =SUM(K81:O81) -> 51245 | K81: 3865 | L81: 42213 | M81: 4167 | N81: 0 | O81: 1000 | P81: 10883 | Q81: 172032 | R81: =Q81/J81 -> 3.3570495 | S81: =J81 -> 51245 | T81: =S81-J81 -> 0 | U81: OK | V81: 1 | W81: =V81/A81 -> 1 | X81: =S81/J81 -> 1
A82: 1 | B82: BONOUA | D82: M100PRT2025051U00082 | E82: M10006328 | G82: KONAN AFFOUE PHILOMENE 0708780111 | H82: Crédit BFR | I82: 46086 | J82: =SUM(K82:O82) -> 251033 | K82: 18144 | L82: 211056 | M82: 20833 | N82: 0 | O82: 1000 | P82: 10898 | Q82: 264731 | R82: =Q82/J82 -> 1.0545665 | S82: =J82 -> 251033 | T82: =S82-J82 -> 0 | U82: OK | V82: 1 | W82: =V82/A82 -> 1 | X82: =S82/J82 -> 1
A83: 1 | B83: BONOUA | D83: M100PRT2025049U00076 | E83: M10006329 | G83: TRAH LOU AMENAN LEA 0709362975 | H83: Crédit BFR | I83: 46086 | J83: =SUM(K83:O83) -> 71009 | K83: 7539 | L83: 56637 | M83: 5833 | N83: 0 | O83: 1000 | P83: 11003 | Q83: 91572 | R83: =Q83/J83 -> 1.289583 | S83: =J83 -> 71009 | T83: =S83-J83 -> 0 | U83: OK | V83: 1 | W83: =V83/A83 -> 1 | X83: =S83/J83 -> 1
A84: 1 | B84: BONOUA | D84: M100PRT2025051U00143 | E84: M10006335 | G84: AHOUAH AHOUAH JOSEPH 0767964995 | H84: Crédit BFR | I84: 46086 | J84: =SUM(K84:O84) -> 151735 | K84: 18639 | L84: 119596 | M84: 12500 | N84: 0 | O84: 1000 | P84: 11040 | Q84: 96113 | R84: =Q84/J84 -> 0.6334267 | S84: =Q84 -> 96113 | T84: =S84-J84 -> -55622 | U84: NOK | W84: =V84/A84 -> 0 | X84: =S84/J84 -> 0.6334267
A85: 1 | B85: BONOUA | D85: M100PRT2025047U00073 | E85: M10006336 | G85: DRABO SOULEYMANE 0708907904 | H85: Crédit BFR | I85: 46086 | J85: =SUM(K85:O85) -> 201980 | K85: 15577 | L85: 168736 | M85: 16667 | N85: 0 | O85: 1000 | P85: 10884 | Q85: 179093 | R85: =Q85/J85 -> 0.8866868 | S85: =Q85 -> 179093 | T85: =S85-J85 -> -22887 | U85: NOK | W85: =V85/A85 -> 0 | X85: =S85/J85 -> 0.8866868
A86: 1 | B86: BONOUA | D86: M100PRT2025047U00085 | E86: M10006353 | G86: OJEDELE EPOUSE AKANJI THERIZER OLUWABUNMI O 0586551407 | H86: Crédit BFR | I86: 46086 | J86: =SUM(K86:O86) -> 71009 | K86: 5091 | L86: 59085 | M86: 5833 | N86: 0 | O86: 1000 | P86: 10901 | Q86: 58444 | R86: =Q86/J86 -> 0.8230506 | S86: =Q86 -> 58444 | T86: =S86-J86 -> -12565 | U86: NOK | W86: =V86/A86 -> 0 | X86: =S86/J86 -> 0.8230506
A87: 1 | B87: BONOUA | D87: M100PRT2025051U00109 | E87: M10006355 | G87: AHOURE ADJIMAN MARIE ROSE 0586147728 | H87: Crédit BFR | I87: 46086 | J87: =SUM(K87:O87) -> 101013 | K87: 8466 | L87: 83214 | M87: 8333 | N87: 0 | O87: 1000 | P87: 10929 | Q87: 225600 | R87: =Q87/J87 -> 2.2333759 | S87: =J87 -> 101013 | T87: =S87-J87 -> 0 | U87: OK | V87: 1 | W87: =V87/A87 -> 1 | X87: =S87/J87 -> 1
A88: 1 | B88: BONOUA | D88: M100PRT2025046U00030 | E88: M10006362 | G88: KOUA ATTOUHO CATHERINE EPOUSE ABLEGUE 0140540694 | H88: Crédit investissement | I88: 46086 | J88: =SUM(K88:O88) -> 31004 | K88: 2557 | L88: 24947 | M88: 2500 | N88: 0 | O88: 1000 | P88: 10913 | Q88: 95480 | R88: =Q88/J88 -> 3.0796026 | S88: =J88 -> 31004 | T88: =S88-J88 -> 0 | U88: OK | V88: 1 | W88: =V88/A88 -> 1 | X88: =S88/J88 -> 1
A89: 1 | B89: BONOUA | D89: M100PRT2025046U00034 | E89: M10006363 | G89: BROU AFFOUE AMANDINE 0505356659 | H89: Crédit BFR | I89: 46086 | J89: =SUM(K89:O89) -> 51007 | K89: 4828 | L89: 41012 | M89: 4167 | N89: 0 | O89: 1000 | P89: 10963 | Q89: 137940 | R89: =Q89/J89 -> 2.7043347 | S89: =J89 -> 51007 | T89: =S89-J89 -> 0 | U89: OK | V89: 1 | W89: =V89/A89 -> 1 | X89: =S89/J89 -> 1
A90: 1 | B90: BONOUA | D90: M100PRT2025046U00062 | E90: M10006383 | G90: YAO N'GUESSAN ROBERT LEON 0170049168 | H90: Crédit BFR | I90: 46086 | J90: =SUM(K90:O90) -> 250622 | K90: 36438 | L90: 193953 | M90: 19231 | N90: 0 | O90: 1000 | P90: 11115 | Q90: 629246 | R90: =Q90/J90 -> 2.5107373 | S90: =J90 -> 250622 | T90: =S90-J90 -> 0 | U90: OK | V90: 1 | W90: =V90/A90 -> 1 | X90: =S90/J90 -> 1
A91: 1 | B91: BONOUA | D91: M100PRT2025049U00067 | E91: M10006384 | G91: BONI KISSI CHARLES 0777398114 | H91: Crédit investissement | I91: 46086 | J91: =SUM(K91:O91) -> 175598 | K91: 29589 | L91: 131120 | M91: 13889 | N91: 0 | O91: 1000 | P91: 10915 | Q91: 1315364 | R91: =Q91/J91 -> 7.4907687 | S91: =J91 -> 175598 | T91: =S91-J91 -> 0 | U91: OK | V91: 1 | W91: =V91/A91 -> 1 | X91: =S91/J91 -> 1
A92: 1 | B92: BONOUA | D92: M100PRT2025049U00058 | E92: M10006387 | G92: BOUBAKAR BOUHOUBOU DIABIRA 0747231515 | H92: Crédit BFR | I92: 46086 | J92: =SUM(K92:O92) -> 201980 | K92: 17905 | L92: 166408 | M92: 16667 | N92: 0 | O92: 1000 | P92: 10938 | Q92: 211418 | R92: =Q92/J92 -> 1.0467274 | S92: =J92 -> 201980 | T92: =S92-J92 -> 0 | U92: OK | V92: 1 | W92: =V92/A92 -> 1 | X92: =S92/J92 -> 1
A93: 1 | B93: BONOUA | D93: M100PRT2025046U00035 | E93: M10006417 | G93: NIAMKE NIANGORAN WILFRIED SCHCNAEL 0777993560 | H93: Crédit BFR | I93: 46086 | J93: =SUM(K93:O93) -> 101490 | K93: 10219 | L93: 81938 | M93: 8333 | N93: 0 | O93: 1000 | P93: 10964 | Q93: 67348 | R93: =Q93/J93 -> 0.66359247 | S93: =Q93 -> 67348 | T93: =S93-J93 -> -34142 | U93: NOK | W93: =V93/A93 -> 0 | X93: =S93/J93 -> 0.66359247
A94: 1 | B94: BONOUA | D94: M100PRT2025049U00110 | E94: M10006427 | G94: AMONKPOLE MAGNIN VICTOIRE 0160757379 | H94: Crédit BFR | I94: 46086 | J94: =SUM(K94:O94) -> 108627 | K94: 13808 | L94: 85486 | M94: 8333 | N94: 0 | O94: 1000 | P94: 11102 | Q94: 72342 | R94: =Q94/J94 -> 0.66596702 | S94: =Q94 -> 72342 | T94: =S94-J94 -> -36285 | U94: NOK | W94: =V94/A94 -> 0 | X94: =S94/J94 -> 0.66596702
A95: 1 | B95: BONOUA | D95: M100PRT2025051U00128 | E95: M10006431 | G95: AMON LUCRECHE VANESSA KANGAH 0102231847 | H95: Crédit BFR | I95: 46086 | J95: =SUM(K95:O95) -> 151020 | K95: 14366 | L95: 123154 | M95: 12500 | N95: 0 | O95: 1000 | P95: 10976 | Q95: 278420 | R95: =Q95/J95 -> 1.8435969 | S95: =J95 -> 151020 | T95: =S95-J95 -> 0 | U95: OK | V95: 1 | W95: =V95/A95 -> 1 | X95: =S95/J95 -> 1
A96: 1 | B96: BONOUA | D96: M100PRT2025051U00125 | E96: M10006432 | G96: KOFFI YVANNE EUNICE AHOUNDJOE AFFALA 0758268541 | H96: Crédit BFR | I96: 46086 | J96: =SUM(K96:O96) -> 51007 | K96: 4789 | L96: 41051 | M96: 4167 | N96: 0 | O96: 1000 | P96: 10977 | Q96: 11097 | R96: =Q96/J96 -> 0.21755837 | S96: =Q96 -> 11097 | T96: =S96-J96 -> -39910 | U96: NOK | W96: =V96/A96 -> 0 | X96: =S96/J96 -> 0.21755837
A97: 1 | B97: BONOUA | D97: M100PRT2025046U00033 | E97: M10006443 | G97: ANOH BISSIE PATRICIA 0171448825 | H97: Crédit BFR | I97: 46086 | J97: =SUM(K97:O97) -> 101013 | K97: 9656 | L97: 82024 | M97: 8333 | N97: 0 | O97: 1000 | P97: 10965 | Q97: 204280 | R97: =Q97/J97 -> 2.022314 | S97: =J97 -> 101013 | T97: =S97-J97 -> 0 | U97: OK | V97: 1 | W97: =V97/A97 -> 1 | X97: =S97/J97 -> 1
A98: 1 | B98: BONOUA | D98: M100PRT2025051U00145 | E98: M10006466 | G98: AZIATO AKOVI OLGA 0171646659 | H98: Crédit BFR | I98: 46086 | J98: =SUM(K98:O98) -> 51007 | K98: 5876 | L98: 39964 | M98: 4167 | N98: 0 | O98: 1000 | P98: 11041 | Q98: 122586 | R98: =Q98/J98 -> 2.4033172 | S98: =J98 -> 51007 | T98: =S98-J98 -> 0 | U98: OK | V98: 1 | W98: =V98/A98 -> 1 | X98: =S98/J98 -> 1
A99: 1 | B99: BONOUA | D99: M100PRT2025051U00126 | E99: M10006468 | G99: AKA AKISSI MIREILLE VINCENTE 0788747606 | H99: Crédit BFR | I99: 46086 | J99: =SUM(K99:O99) -> 51007 | K99: 4789 | L99: 41051 | M99: 4167 | N99: 0 | O99: 1000 | P99: 10978 | Q99: 40113 | R99: =Q99/J99 -> 0.78642147 | S99: =Q99 -> 40113 | T99: =S99-J99 -> -10894 | U99: NOK | W99: =V99/A99 -> 0 | X99: =S99/J99 -> 0.78642147
A100: 1 | B100: BONOUA | D100: M100PRT2025048U00054 | E100: M10006475 | G100: FOFANA MAIMOUNA 0565713774 | H100: Crédit BFR | I100: 46086 | J100: =SUM(K100:O100) -> 30812 | K100: 4142 | L100: 23362 | M100: 2308 | N100: 0 | O100: 1000 | P100: 11092 | Q100: 109399 | R100: =Q100/J100 -> 3.5505323 | S100: =J100 -> 30812 | T100: =S100-J100 -> 0 | U100: OK | V100: 1 | W100: =V100/A100 -> 1 | X100: =S100/J100 -> 1
...
